fuse_webhdfs-0.6.3.dist-info/DESCRIPTION.rst
fuse_webhdfs-0.6.3.dist-info/METADATA
fuse_webhdfs-0.6.3.dist-info/RECORD
fuse_webhdfs-0.6.3.dist-info/WHEEL
fuse_webhdfs-0.6.3.dist-info/metadata.json
fuse_webhdfs-0.6.3.dist-info/top_level.txt
pywebhdfs/__init__.py
pywebhdfs/errors.py
pywebhdfs/operations.py
pywebhdfs/webhdfs.py
