Metadata-Version: 2.0
Name: fuse-webhdfs
Version: 0.6.3
Summary: Mount Knox-protected WebHDFS on your local Linux or Mac file system
Home-page: https://github.com/IBM/fuse-webhdfs
Author: Sasa Tomic
Author-email: sat@zurich.ibm.com
License: Apache 2.0
Project-URL: Bug Reports, https://github.com/IBM/fuse-webhdfs/issues
Project-URL: Source, https://github.com/IBM/fuse-webhdfs
Keywords: Knox WebHDFS fuse mount remote HDFS
Platform: UNKNOWN
Classifier: Development Status :: 4 - Beta
Classifier: Intended Audience :: Developers
Classifier: Topic :: Software Development :: Build Tools
Classifier: License :: OSI Approved :: Apache Software License
Classifier: Programming Language :: Python :: 3
Classifier: Programming Language :: Python :: 3.4
Classifier: Programming Language :: Python :: 3.5
Classifier: Programming Language :: Python :: 3.6
Requires-Python: >=3.3.*, <4
Requires-Dist: fusepy
Provides-Extra: dev
Requires-Dist: check-manifest; extra == 'dev'
Provides-Extra: test
Requires-Dist: coverage; extra == 'test'
